<?xml version="1.0" encoding="utf-8" ?><dwsync><file name=".DS_Store" server="ftp.hostinguruguay.info/app/" local="3477581129" remote="7772540476" Dst="-1" /><file name="admin.js" server="ftp.hostinguruguay.info/app/" local="3477606347" remote="-4611697731620579372" Dst="-1" /><file name="ajax.js" server="ftp.hostinguruguay.info/app/" local="3477273635" remote="-4611698350095888836" Dst="-1" /><file name="application.js" server="ftp.hostinguruguay.info/app/" local="3477273635" remote="-4611698350095888836" Dst="-1" /><file name="bootstrap.min.js" server="ftp.hostinguruguay.info/app/" local="3477358828" remote="7772540476" Dst="-1" /><file name="jquery.dropdown.js" server="ftp.hostinguruguay.info/app/" local="3477273635" remote="-4611698350095888836" Dst="-1" /><file name="jquery.fileupload.js" server="ftp.hostinguruguay.info/app/" local="3477273635" remote="-4611698350095888836" Dst="-1" /><file name="jquery.iframe-transport.js" server="ftp.hostinguruguay.info/app/" local="3477273635" remote="-4611698350095888836" Dst="-1" /><file name="jquery.jcarousel.min.js" server="ftp.hostinguruguay.info/app/" local="3477273635" remote="-4611698350095888836" Dst="-1" /><file name="jquery.js" server="ftp.hostinguruguay.info/app/" local="3477273635" remote="-4611698350095888836" Dst="-1" /><file name="jquery.pikachoose.min.js" server="ftp.hostinguruguay.info/app/" local="3477273635" remote="-4611698350095888836" Dst="-1" /><file name="jquery.touchwipe.min.js" server="ftp.hostinguruguay.info/app/" local="3477273635" remote="-4611698350095888836" Dst="-1" /><file name="modernizr.js" server="ftp.hostinguruguay.info/app/" local="3477273635" remote="-4611698350095888836" Dst="-1" /><file name="jquery-ui.js" server="ftp.hostinguruguay.info/app/" local="3477273635" remote="-4611698350095888836" Dst="-1" /><file name="owl-carousel.js" server="ftp.hostinguruguay.info/app/" local="3477273635" remote="-4611698350095888836" Dst="-1" /><file name="same-height.js" server="ftp.hostinguruguay.info/app/" local="3477273635" remote="-4611698350095888836" Dst="-1" /><file name="slider.js" server="ftp.hostinguruguay.info/app/" local="3477273635" remote="-4611698350095888836" Dst="-1" /></dwsync>